sentry_dramatiq_cron_logger/__about__.py
sentry_dramatiq_cron_logger/__init__.py
sentry_dramatiq_cron_logger-0.0.1.dist-info/METADATA
sentry_dramatiq_cron_logger-0.0.1.dist-info/WHEEL
sentry_dramatiq_cron_logger-0.0.1.dist-info/licenses/LICENSE.txt
sentry_dramatiq_cron_logger-0.0.1.dist-info/RECORD
