Metadata-Version: 2.1
Name: sentry-dramatiq-cron-logger
Version: 0.0.1
Summary: Sentry Cron Logging Package for Dramatiq Actors
Project-URL: Documentation, https://github.com/unknown/sentry-dramatiq-cron-logger#readme
Project-URL: Issues, https://github.com/unknown/sentry-dramatiq-cron-logger/issues
Project-URL: Source, https://github.com/unknown/sentry-dramatiq-cron-logger
Author-email: Zeke Zumbro <jezumbro@gmail.com>
License-Expression: MIT
License-File: LICENSE.txt
Classifier: Development Status :: 4 - Beta
Classifier: Programming Language :: Python
Classifier: Programming Language :: Python :: 3.7
Classifier: Programming Language :: Python :: 3.8
Classifier: Programming Language :: Python :: 3.9
Classifier: Programming Language :: Python :: 3.10
Classifier: Programming Language :: Python :: 3.11
Classifier: Programming Language :: Python :: Implementation :: CPython
Classifier: Programming Language :: Python :: Implementation :: PyPy
Requires-Python: >=3.7
Requires-Dist: dramatiq
Requires-Dist: requests
